setup.cfg
setup.py
lmi/__init__.py
lmi/scripts/__init__.py
lmi/scripts/powermanagement/__init__.py
lmi/scripts/powermanagement/cmd.py
openlmi_scripts_powermanagement.egg-info/PKG-INFO
openlmi_scripts_powermanagement.egg-info/SOURCES.txt
openlmi_scripts_powermanagement.egg-info/dependency_links.txt
openlmi_scripts_powermanagement.egg-info/entry_points.txt
openlmi_scripts_powermanagement.egg-info/namespace_packages.txt
openlmi_scripts_powermanagement.egg-info/requires.txt
openlmi_scripts_powermanagement.egg-info/top_level.txt