Metadata-Version: 1.1
Name: openlmi-scripts-powermanagement
Version: 0.2.8
Summary: LMI command for power management.
Home-page: https://github.com/openlmi/openlmi-scripts
Author: Radek Novacek
Author-email: rnovacek@redhat.com
License: BSD
Download-URL: https://github.com/openlmi/openlmi-scripts/tarball/master
Platform: Any
Classifier: License :: OSI Approved :: BSD License
Classifier: Operating System :: POSIX :: Linux
Classifier: Topic :: System :: Systems Administration
Classifier: Programming Language :: Python
Classifier: Programming Language :: Python :: 2
Classifier: Programming Language :: Python :: 2.7
Classifier: Intended Audience :: Developers
Classifier: Environment :: Console
